docker_image_diff-0.1.0.dist-info/licenses/LICENSE
dockerdiff/__init__.py
dockerdiff/main.py
docker_image_diff-0.1.0.dist-info/METADATA
docker_image_diff-0.1.0.dist-info/WHEEL
docker_image_diff-0.1.0.dist-info/entry_points.txt
docker_image_diff-0.1.0.dist-info/top_level.txt
docker_image_diff-0.1.0.dist-info/RECORD
