Metadata-Version: 2.4
Name: docker-image-diff
Version: 0.1.0
Summary: Generate and apply diffs between Docker image tar archives
Home-page: https://github.com/junghyun3/docker-image-diff
Author: Junghyun Kwon
Author-email: 
License: Apache-2.0
Classifier: Programming Language :: Python :: 3
Classifier: Programming Language :: Python :: 3.10
Classifier: License :: OSI Approved :: Apache Software License
Classifier: Operating System :: OS Independent
Requires-Python: >=3.10
License-File: LICENSE
Dynamic: author
Dynamic: classifier
Dynamic: description
Dynamic: description-content-type
Dynamic: home-page
Dynamic: license
Dynamic: license-file
Dynamic: requires-python
Dynamic: summary
